{
  "donations": [
    {
      "amount": "100",
      "cardNumber": "1234567890123456",
      "cardHolder": "John Doe",
      "expiryDate": "2027-12",
      "cvv": "123",
      "blogID": "1",
      "id": "1"
    },
    {
      "id": "86bc",
      "amount": "20",
      "cardNumber": "213712983719373",
      "cardHolder": "Test Johnson",
      "expiryDate": "2027-05",
      "cvv": "590",
      "blogID": "2"
    },
    {
      "id": "2ebb",
      "amount": "25",
      "cardNumber": "2938293823",
      "cardHolder": "Dylan",
      "expiryDate": "2032-04",
      "cvv": "444",
      "blogID": "8"
    },
    {
      "id": "7d56",
      "amount": "30",
      "cardNumber": "34792387423",
      "cardHolder": "Dylan Again",
      "expiryDate": "3000-05",
      "cvv": "273",
      "blogID": "8"
    }
  ]
}